pacsman/__init__.py
pacsman/base_client.py
pacsman/base_client_test.py
pacsman/dcmtk_client.py
pacsman/dcmtk_client_test.py
pacsman/filesystem_client_test.py
pacsman/filesystem_dev_client.py
pacsman/integration_test.py
pacsman/pynetdicom_client.py
pacsman/upload_test.py
pacsman/utils.py
pacsman/utils_test.py
pacsman-0.1.8.dist-info/LICENSE
pacsman-0.1.8.dist-info/METADATA
pacsman-0.1.8.dist-info/WHEEL
pacsman-0.1.8.dist-info/dependency_links.txt
pacsman-0.1.8.dist-info/top_level.txt
pacsman-0.1.8.dist-info/RECORD
