Metadata-Version: 2.1
Name: pacsman
Version: 0.1.8
Summary: pacsman: Picture Archiving and Communication System Manager And Numpifier
Home-page: https://github.com/innolitics/pacsman
Author: Innolitics, LLC
Author-email: info@innolitics.com
License: MIT
Keywords: scientific image
Classifier: Development Status :: 1 - Planning
Classifier: Intended Audience :: Developers
Classifier: Intended Audience :: Healthcare Industry
Classifier: Topic :: Scientific/Engineering :: Medical Science Apps.
Classifier: Topic :: Communications
Classifier: License :: OSI Approved :: MIT License
Classifier: Programming Language :: Python :: 3
Classifier: Programming Language :: Python :: 3.6
License-File: LICENSE
Requires-Dist: pydicom (>=1.3)
Requires-Dist: pynetdicom (>=2)
Requires-Dist: numpy
Requires-Dist: pypng
Requires-Dist: scipy
